exceptlib.py
exceptlib-2024.1.dist-info/LICENSE.md
exceptlib-2024.1.dist-info/METADATA
exceptlib-2024.1.dist-info/WHEEL
exceptlib-2024.1.dist-info/top_level.txt
exceptlib-2024.1.dist-info/RECORD
