Metadata-Version: 2.1
Name: exceptlib
Version: 2024.1
Summary: Additional exception handling mechanisms
Author-email: Will Fatherley <wfatherley@proton.me>
Maintainer-email: Will Fatherley <wfatherley@proton.me>
License: Copyright 2024 Will Fatherley
Project-URL: repository, https://github.com/wfatherley/exceptlib.git
Classifier: Intended Audience :: Developers
Classifier: Topic :: Software Development :: Quality Assurance
Classifier: License :: OSI Approved :: MIT License
Classifier: Programming Language :: Python :: 3
Requires-Python: >=3.9
License-File: LICENSE.md
